dcscope/__init__.py
dcscope/__main__.py
dcscope/_version.py
dcscope/extensions.py
dcscope/idiom.py
dcscope/meta_tool.py
dcscope/plot_cache.py
dcscope/session.py
dcscope/util.py
dcscope/gui/__init__.py
dcscope/gui/main.py
dcscope/gui/main.ui
dcscope/gui/pipeline_plot.py
dcscope/gui/pipeline_plot.ui
dcscope/gui/preferences.py
dcscope/gui/preferences.ui
dcscope/gui/update.py
dcscope/gui/analysis/__init__.py
dcscope/gui/analysis/ana_basins.py
dcscope/gui/analysis/ana_basins.ui
dcscope/gui/analysis/ana_filter.py
dcscope/gui/analysis/ana_filter.ui
dcscope/gui/analysis/ana_log.py
dcscope/gui/analysis/ana_log.ui
dcscope/gui/analysis/ana_meta.py
dcscope/gui/analysis/ana_meta.ui
dcscope/gui/analysis/ana_plot.py
dcscope/gui/analysis/ana_plot.ui
dcscope/gui/analysis/ana_slot.py
dcscope/gui/analysis/ana_slot.ui
dcscope/gui/analysis/ana_tables.py
dcscope/gui/analysis/ana_tables.ui
dcscope/gui/analysis/ana_view.py
dcscope/gui/analysis/ana_view.ui
dcscope/gui/analysis/dlg_slot_reorder.py
dcscope/gui/analysis/dlg_slot_reorder.ui
dcscope/gui/bulk/__init__.py
dcscope/gui/bulk/bulk_emodulus.py
dcscope/gui/bulk/bulk_emodulus.ui
dcscope/gui/compute/__init__.py
dcscope/gui/compute/comp_lme4.py
dcscope/gui/compute/comp_lme4.ui
dcscope/gui/compute/comp_lme4_dataset.py
dcscope/gui/compute/comp_lme4_dataset.ui
dcscope/gui/compute/comp_lme4_results.py
dcscope/gui/compute/comp_lme4_results.ui
dcscope/gui/compute/comp_stats.py
dcscope/gui/compute/comp_stats.ui
dcscope/gui/dcor/__init__.py
dcscope/gui/dcor/dcor.ui
dcscope/gui/export/__init__.py
dcscope/gui/export/e2data.py
dcscope/gui/export/e2data.ui
dcscope/gui/export/e2filter.py
dcscope/gui/export/e2filter.ui
dcscope/gui/export/e2plot.py
dcscope/gui/export/e2plot.ui
dcscope/gui/matrix/__init__.py
dcscope/gui/matrix/block_matrix.py
dcscope/gui/matrix/block_matrix.ui
dcscope/gui/matrix/data_matrix.py
dcscope/gui/matrix/dm_dataset.py
dcscope/gui/matrix/dm_dataset.ui
dcscope/gui/matrix/dm_element.py
dcscope/gui/matrix/dm_element.ui
dcscope-2.23.1.dist-info/licenses/LICENSE
dcscope-2.23.1.dist-info/METADATA
dcscope-2.23.1.dist-info/WHEEL
dcscope-2.23.1.dist-info/entry_points.txt
dcscope-2.23.1.dist-info/top_level.txt
dcscope-2.23.1.dist-info/RECORD
