Metadata-Version: 2.4
Name: dcscope
Version: 2.23.1
Summary: User interface for deformability cytometry (DC)
Author: Benedikt Hartmann, Eoghan O'Connell, Maximilian Schlögel, Paul Müller, Raghava Alajangi
Maintainer-email: Paul Müller <dev@craban.de>
License-Expression: GPL-3.0-or-later
Project-URL: source, https://github.com/DC-analysis/DCscope
Project-URL: tracker, https://github.com/DC-analysis/DCscope/issues
Project-URL: documentation, https://dcscope.readthedocs.io
Project-URL: changelog, https://github.com/DC-analysis/DCscope/blob/main/CHANGELOG
Keywords: RT-DC,DC,deformability,cytometry
Classifier: Operating System :: OS Independent
Classifier: Programming Language :: Python :: 3
Classifier: Intended Audience :: Science/Research
Requires-Python: <4,>=3.9
License-File: LICENSE
Requires-Dist: dclab[dcor,export,http,s3]>=0.67.2
Requires-Dist: h5py>=2.8.0
Requires-Dist: numpy>=1.21
Requires-Dist: pygments
Requires-Dist: pyqt6
Requires-Dist: pyqtgraph==0.13.6
Requires-Dist: requests>=2.31.0
Requires-Dist: scipy>=1.10.0
Dynamic: license-file
